{
    "type": "object",
    "properties": {
        "profileId": {
            "description": "The ID of the profile",
            "type": "integer"
        },
        "countryCode": {
            "description": "The country code of the profile",
            "type": "string"
        },
        "day": {
            "type": "string",
            "format": "date-time"
        },
        "campaignId": {
            "type": ["null", "string"]
        },
        "campaignName": {
            "type": ["null", "string"]
        },
        "adGroupId": {
            "type": ["null", "string"]
        },
        "adGroupName": {
            "type": ["null", "string"]
        },
        "currency": {
            "type": ["null", "string"]
        },
        "asin": {
            "type": ["null", "string"]
        },
        "otherAsin": {
            "type": ["null", "string"]
        },
        "sku": {
            "type": ["null", "string"]
        },
        "attributedSales14dOtherSKU": {
            "type": ["null", "number"]
        },
        "attributedSales30dOtherSKU": {
            "type": ["null", "number"]
        },
        "attributedUnitsOrdered14dOtherSKU": {
            "type": ["null", "number"]
        },
        "attributedUnitsOrdered30dOtherSKU": {
            "type": ["null", "number"]
        }
    }
}
